run.py
setup.py
npm_helper/__init__.py
npm_helper/data.py
npm_helper/entry.py
npm_helper/observer.py
npm_helper.egg-info/PKG-INFO
npm_helper.egg-info/SOURCES.txt
npm_helper.egg-info/dependency_links.txt
npm_helper.egg-info/entry_points.txt
npm_helper.egg-info/not-zip-safe
npm_helper.egg-info/requires.txt
npm_helper.egg-info/top_level.txt
npm_helper/spiders/__init__.py
npm_helper/spiders/spider_list.py
npm_helper/spiders/spider_page.py