Metadata-Version: 1.1
Name: npm-helper
Version: 0.20
Summary: npm website search is sooo silly and inconvenience. That's why this plugin born
Home-page: https://github.com/ecmadao/npm-helper
Author: ecmadao
Author-email: wlec@outlook.com
License: MIT
Keywords: npm,search,github,spider
Platform: any
Classifier: Environment :: Console
Classifier: Programming Language :: Python
Classifier: Programming Language :: Python :: 3.5
Classifier: Programming Language :: Python :: Implementation :: CPython
